vitaldb/__init__.py
vitaldb/api.py
vitaldb/dataset.py
vitaldb/utils.py
vitaldb-1.5.7.dist-info/licenses/LICENSE
vitaldb-1.5.7.dist-info/METADATA
vitaldb-1.5.7.dist-info/WHEEL
vitaldb-1.5.7.dist-info/top_level.txt
vitaldb-1.5.7.dist-info/RECORD
