Metadata-Version: 2.4
Name: vitaldb
Version: 1.5.7
Summary: VitalDB Python Libray
Author-email: VitalLab <vital@snu.ac.kr>
License-Expression: MIT
Requires-Python: >=3.0
License-File: LICENSE
Requires-Dist: numpy
Requires-Dist: pandas
Requires-Dist: requests
Requires-Dist: wfdb
Dynamic: license-file
